Sem3/Verilog/lab1/example1.v
module example1 (A,B,C,D,f);
    input A,B,C,D;
    output f;
    assign f=C|(A&~D);
endmodule

Sem3/Verilog/lab1/example1_tb.v
`timescale 1ns/1ns
`include "example1.v"
module example1_tb;
reg A,B,C,D;
wire f;
example1 ex1(A,B,C,D,f);
initial begin
    $dumpfile("example1_tb.vcd");
    $dumpvars(0,example1_tb);
    A=0;B=0;C=0;D=0;#20;
    A=0;B=0;C=0;D=1;#20;
    A=0;B=0;C=1;D=0;#20;
    A=0;B=0;C=1;D=1;#20;
    A=0;B=1;C=0;D=0;#20;
    A=0;B=1;C=0;D=1;#20;
    A=0;B=1;C=1;D=0;#20;
    A=0;B=1;C=1;D=1;#20;
    A=1;B=0;C=0;D=0;#20;
    A=1;B=0;C=0;D=1;#20;
    A=1;B=0;C=1;D=0;#20;
    A=1;B=0;C=1;D=1;#20;
    A=1;B=1;C=0;D=0;#20;
    A=1;B=1;C=0;D=1;#20;
    A=1;B=1;C=1;D=0;#20;
    A=1;B=1;C=1;D=1;#20;
    $display("Test completed");
end
endmodule

Sem3/Verilog/lab1/example1_tb.vcd
$date
	Thu Sep  7 11:26:16 2023
$end
$version
	Icarus Verilog
$end
$timescale
	1ns
$end
$scope module example1_tb $end
$var wire 1 ! f $end
$var reg 1 " A $end
$var reg 1 # B $end
$var reg 1 $ C $end
$var reg 1 % D $end
$scope module ex1 $end
$var wire 1 " A $end
$var wire 1 # B $end
$var wire 1 $ C $end
$var wire 1 % D $end
$var wire 1 ! f $end
$upscope $end
$upscope $end
$enddefinitions $end
$comment Show the parameter values. $end
$dumpall
$end
#0
$dumpvars
0%
0$
0#
0"
0!
$end
#20
1%
#40
1!
0%
1$
#60
1%
#80
0!
0%
0$
1#
#100
1%
#120
1!
0%
1$
#140
1%
#160
1!
0%
0$
0#
1"
#180
0!
1%
#200
1!
0%
1$
#220
1%
#240
1!
0%
0$
1#
#260
0!
1%
#280
1!
0%
1$
#300
1%
