Sem3/Verilog/lab1/ivk_ad2.v
module ivk_ad2 (x1,x2,x3,x4,f);
    input x1,x2,x3,x4;
    output f;
    assign f=((x1&x2)&(x3|x4))|((x3&x4)&(x1|x2));
endmodule

Sem3/Verilog/lab1/ivk_ad2_tb.v
`timescale 1ns/1ns
`include "ivk_ad2.v"
module ivk_ad2_tb ;
reg x1,x2,x3,x4;
wire f;
ivk_ad2 ivk(x1,x2,x3,x4,f);
initial begin
    $dumpfile("ivk_ad2_tb.vcd");
    $dumpvars(0,ivk_ad2_tb);
    x1=0;x2=0;x3=0;x4=0;#20;
    x1=0;x2=0;x3=0;x4=1;#20;
    x1=0;x2=0;x3=1;x4=0;#20;
    x1=0;x2=0;x3=1;x4=1;#20;
    x1=0;x2=1;x3=0;x4=0;#20;
    x1=0;x2=1;x3=0;x4=1;#20;
    x1=0;x2=1;x3=1;x4=0;#20;
    x1=0;x2=1;x3=1;x4=1;#20;
    x1=1;x2=0;x3=0;x4=0;#20;
    x1=1;x2=0;x3=0;x4=1;#20;
    x1=1;x2=0;x3=1;x4=0;#20;
    x1=1;x2=0;x3=1;x4=1;#20;
    x1=1;x2=1;x3=0;x4=0;#20;
    x1=1;x2=1;x3=0;x4=1;#20;
    x1=1;x2=1;x3=1;x4=0;#20;
    x1=1;x2=1;x3=1;x4=1;#20;
    $display("Test completed");
end
endmodule

Sem3/Verilog/lab1/ivk_ad2_tb.vcd
$date
	Thu Sep  7 12:22:51 2023
$end
$version
	Icarus Verilog
$end
$timescale
	1ns
$end
$scope module ivk_ad2_tb $end
$var wire 1 ! f $end
$var reg 1 " x1 $end
$var reg 1 # x2 $end
$var reg 1 $ x3 $end
$var reg 1 % x4 $end
$scope module ivk $end
$var wire 1 ! f $end
$var wire 1 " x1 $end
$var wire 1 # x2 $end
$var wire 1 $ x3 $end
$var wire 1 % x4 $end
$upscope $end
$upscope $end
$enddefinitions $end
$comment Show the parameter values. $end
$dumpall
$end
#0
$dumpvars
0%
0$
0#
0"
0!
$end
#20
1%
#40
0%
1$
#60
1%
#80
0%
0$
1#
#100
1%
#120
0%
1$
#140
1!
1%
#160
0!
0%
0$
0#
1"
#180
1%
#200
0%
1$
#220
1!
1%
#240
0!
0%
0$
1#
#260
1!
1%
#280
0%
1$
#300
1%
