Sem3/Verilog/lab2/lab2_2.v
// module lab2_2(Cin,x,y,Cout,S);
// input Cin,x,y;
// output Cout,S;
// wire g;
// assign g= x^y;
// assign S= Cin^g;
// assign Cout= (Cin &y)|(x&y)|(Cin&x);
// endmodule
module lab2_2(Cin,x,Cout,S);
input Cin;
input [1:0]x;
output reg Cout,S;
always @(x,Cin)
begin
    S=x[0]^x[1]^Cin;
    Cout= (Cin &x[1])|(x[0]&x[1])|(Cin&x[0]);
end
endmodule

Sem3/Verilog/lab2/lab2_2_tb.v
`timescale 1ns/1ns
`include "lab2_2.v"
module lab2_2_tb;
reg [1:0]x;
reg Cin;
wire S,Cout;
lab2_2 l22 (Cin,x,Cout,S);
initial begin
    $dumpfile("lab2_2_tb.vcd");
    $dumpvars(0,lab2_2_tb);
    Cin=0;x[0]=0;x[1]=0;#20;
    Cin=0;x[0]=0;x[1]=1;#20;
    Cin=0;x[0]=1;x[1]=0;#20;
    Cin=0;x[0]=1;x[1]=1;#20;
    Cin=1;x[0]=0;x[1]=0;#20;
    Cin=1;x[0]=0;x[1]=1;#20;
    Cin=1;x[0]=1;x[1]=0;#20;
    Cin=1;x[0]=1;x[1]=1;#20;
    $display("Test Completed");
end
endmodule

Sem3/Verilog/lab2/lab2_2_tb.vcd
$date
	Sat Nov 18 20:22:07 2023
$end
$version
	Icarus Verilog
$end
$timescale
	1ns
$end
$scope module lab2_2_tb $end
$var wire 1 ! S $end
$var wire 1 " Cout $end
$var reg 1 # Cin $end
$var reg 2 $ x [1:0] $end
$scope module l22 $end
$var wire 1 # Cin $end
$var wire 2 % x [1:0] $end
$var reg 1 " Cout $end
$var reg 1 ! S $end
$upscope $end
$upscope $end
$enddefinitions $end
$comment Show the parameter values. $end
$dumpall
$end
#0
$dumpvars
b0 %
b0 $
0#
0"
0!
$end
#20
1!
b10 $
b10 %
#40
b1 $
b1 %
#60
1"
0!
b11 $
b11 %
#80
0"
1!
b0 $
b0 %
1#
#100
1"
0!
b10 $
b10 %
#120
b1 $
b1 %
#140
1!
b11 $
b11 %
