Sem3/Verilog/lab2/lab2_1.v
module lab2_1(A,B,C,D,g,f);
input A,B,C,D;
output f,g;
wire g;
assign g= C^D;
assign f= (A&g)|(B&~g);
endmodule

Sem3/Verilog/lab2/lab2_1_tb.v
`timescale 1ns/1ns
`include "lab2_1.v"
module lab2_1_tb;
reg A,B,C,D;
wire f,g;
lab2_1 l21 (A,B,C,D,g,f);
initial begin
    $dumpfile("lab2_1_tb.vcd");
    $dumpvars(0,lab2_1_tb);
    A=0;B=0;C=0;D=0;#20;
    A=0;B=0;C=0;D=1;#20;
    A=0;B=0;C=1;D=0;#20;
    A=0;B=0;C=1;D=1;#20;
    A=0;B=1;C=0;D=0;#20;
    A=0;B=1;C=0;D=1;#20;
    A=0;B=1;C=1;D=0;#20;
    A=0;B=1;C=1;D=1;#20;
    A=1;B=0;C=0;D=0;#20;
    A=1;B=0;C=0;D=1;#20;
    A=1;B=0;C=1;D=0;#20;
    A=1;B=0;C=1;D=1;#20;
    A=1;B=1;C=0;D=0;#20;
    A=1;B=1;C=0;D=1;#20;
    A=1;B=1;C=1;D=0;#20;
    A=1;B=1;C=1;D=1;#20;
    $display("Test completed");
end
endmodule

Sem3/Verilog/lab2/lab2_1_tb.vcd
$date
	Sat Sep  9 10:04:45 2023
$end
$version
	Icarus Verilog
$end
$timescale
	1ns
$end
$scope module lab2_1_tb $end
$var wire 1 ! g $end
$var wire 1 " f $end
$var reg 1 # A $end
$var reg 1 $ B $end
$var reg 1 % C $end
$var reg 1 & D $end
$scope module l21 $end
$var wire 1 # A $end
$var wire 1 $ B $end
$var wire 1 % C $end
$var wire 1 & D $end
$var wire 1 " f $end
$var wire 1 ! g $end
$upscope $end
$upscope $end
$enddefinitions $end
$comment Show the parameter values. $end
$dumpall
$end
#0
$dumpvars
0&
0%
0$
0#
0"
0!
$end
#20
1!
1&
#40
0&
1%
#60
0!
1&
#80
1"
0&
0%
1$
#100
0"
1!
1&
#120
0&
1%
#140
1"
0!
1&
#160
0"
0&
0%
0$
1#
#180
1"
1!
1&
#200
0&
1%
#220
0"
0!
1&
#240
1"
0&
0%
1$
#260
1!
1&
#280
0&
1%
#300
0!
1&
