Sem3/Verilog/lab3/additional/bcd_excess.v
module bcd_excess(a,e);
input [3:0]a;
output reg [3:0]e;
always @(a)
begin
    e[0]=(~a[0]&~a[3])+(~a[1]&~a[0]&~a[2]);
    e[1]=(~a[1]&a[0]&~a[2])|(~a[3]&~(a[1]^a[0]));
    e[2]=(~a[1]&a[0]&~a[2])|(a[1]&~a[3]&~a[2])|(~a[1]&~a[0]&~a[3]&a[2]);
    e[3]=(a[0]&~a[3]&a[2])|(a[1]&~a[3]&a[2])|(~a[1]&a[3]&~a[2]);
end
endmodule

Sem3/Verilog/lab3/additional/bcd_excess_tb.v
`timescale 1ns/1ns
`include "bcd_excess.v"
module bcd_excess_tb;
reg[3:0]a;
wire[3:0]e;
bcd_excess be(a,e);
initial begin
    $dumpfile("bcd_excess_tb.vcd");
    $dumpvars(0,bcd_excess_tb);
    a=0;#20;
    a=1;#20;
    a=2;#20;
    a=3;#20;
    a=4;#20;
    a=5;#20;
    a=6;#20;
    a=7;#20;
    a=8;#20;
    a=9;#20;
    $display("Test complete");
end
endmodule

Sem3/Verilog/lab3/additional/bcd_excess_tb.vcd
$date
	Sun Sep 10 13:29:42 2023
$end
$version
	Icarus Verilog
$end
$timescale
	1ns
$end
$scope module bcd_excess_tb $end
$var wire 4 ! e [3:0] $end
$var reg 4 " a [3:0] $end
$scope module be $end
$var wire 4 # a [3:0] $end
$var reg 4 $ e [3:0] $end
$upscope $end
$upscope $end
$enddefinitions $end
$comment Show the parameter values. $end
$dumpall
$end
#0
$dumpvars
b10 $
b0 #
b0 "
b10 !
$end
#20
b110 !
b110 $
b1 "
b1 #
#40
b101 !
b101 $
b10 "
b10 #
#60
b110 !
b110 $
b11 "
b11 #
#80
b111 !
b111 $
b100 "
b100 #
#100
b1000 !
b1000 $
b101 "
b101 #
#120
b1001 !
b1001 $
b110 "
b110 #
#140
b1010 !
b1010 $
b111 "
b111 #
#160
b1001 !
b1001 $
b1000 "
b1000 #
#180
b1110 !
b1110 $
b1001 "
b1001 #
